news_scrap.py
newscrap-0.1.0.dist-info/licenses/LICENSE
newscrap-0.1.0.dist-info/METADATA
newscrap-0.1.0.dist-info/WHEEL
newscrap-0.1.0.dist-info/entry_points.txt
newscrap-0.1.0.dist-info/top_level.txt
newscrap-0.1.0.dist-info/RECORD
