Metadata-Version: 2.4
Name: newscrap
Version: 0.1.0
Summary: Google News Scraper CLI for OSINT and research
Home-page: https://github.com/opsysdebug/NewsCrap
Author: opsysdebug
Author-email: your-email@example.com
Requires-Python: >=3.7
License-File: LICENSE
Requires-Dist: requests>=2.28.0
Requires-Dist: beautifulsoup4>=4.11.0
Requires-Dist: fake-useragent>=1.2.0
Requires-Dist: schedule>=1.1.0
Requires-Dist: Jinja2>=3.1.0
Dynamic: author
Dynamic: author-email
Dynamic: home-page
Dynamic: license-file
